pew/__init__.py
pew/__main__.py
pew/_print_utils.py
pew/_utils.py
pew/pew.py
pew/shell_config/_pew
pew/shell_config/complete.bash
pew/shell_config/complete.fish
pew/shell_config/complete.zsh
pew/shell_config/complete_deploy
pew/shell_config/init.bash
pew/shell_config/init.fish
pew/shell_config/init.zsh
pew-1.1.5.dist-info/DESCRIPTION.rst
pew-1.1.5.dist-info/METADATA
pew-1.1.5.dist-info/RECORD
pew-1.1.5.dist-info/WHEEL
pew-1.1.5.dist-info/entry_points.txt
pew-1.1.5.dist-info/metadata.json
pew-1.1.5.dist-info/top_level.txt
