Metadata-Version: 2.0
Name: pew
Version: 1.1.5
Summary: tool to manage multiple virtualenvs written in pure python
Home-page: https://github.com/berdario/pew
Author: Dario Bertini
Author-email: berdario@gmail.com
License: MIT License
Platform: UNKNOWN
Classifier: Programming Language :: Python :: 2
Classifier: Programming Language :: Python :: 3
Classifier: Intended Audience :: Developers
Classifier: Environment :: Console
Provides-Extra: pythonz
Requires-Dist: virtualenv (>=1.11)
Requires-Dist: virtualenv-clone (>=0.2.5)
Requires-Dist: setuptools (>=17.1)
Requires-Dist: argparse; python_version=="2.6"
Requires-Dist: pathlib; python_version=="2.6"
Requires-Dist: backports.shutil-get-terminal-size; python_version=="2.6"
Requires-Dist: shutilwhich; python_version=="2.6"
Requires-Dist: pathlib; python_version=="2.7"
Requires-Dist: backports.shutil-get-terminal-size; python_version=="2.7"
Requires-Dist: shutilwhich; python_version=="2.7"
Requires-Dist: pathlib; python_version=="3.2"
Requires-Dist: backports.shutil-get-terminal-size; python_version=="3.2"
Requires-Dist: shutilwhich; python_version=="3.2"
Requires-Dist: pathlib; python_version=="3.3"
Requires-Dist: psutil (==5.3.1); sys_platform=="win32"
Provides-Extra: pythonz
Requires-Dist: pythonz-bd (>=1.10.2); extra == 'pythonz'
